{
  "_class": "artboard",
  "backgroundColor": {
    "_class": "color",
    "alpha": 1,
    "blue": 1,
    "green": 1,
    "red": 1
  },
  "booleanOperation": 0,
  "do_objectID": "C08088D2-1D6F-4EBA-8F4A-242A937AED60",
  "exportOptions": {
    "_class": "exportOptions",
    "exportFormats": [
    ],
    "includedLayerIds": [
    ],
    "layerOptions": 0,
    "shouldTrim": false
  },
  "frame": {
    "_class": "rect",
    "constrainProportions": false,
    "height": 640,
    "width": 360,
    "x": 1740,
    "y": 1101
  },
  "hasBackgroundColor": true,
  "hasClickThrough": false,
  "horizontalRulerData": {
    "_class": "rulerData",
    "base": 0,
    "guides": [
    ]
  },
  "includeBackgroundColorInExport": true,
  "includeInCloudUpload": true,
  "isFixedToViewport": false,
  "isFlippedHorizontal": false,
  "isFlippedVertical": false,
  "isFlowHome": false,
  "isLocked": false,
  "isVisible": true,
  "layerListExpandedType": 1,
  "layers": [
    {
      "class": "group",
      "id": "1575D1A8-600F-44F7-BF23-2F9FD114ACF3"
    },
    {
      "class": "symbolInstance",
      "id": "DC5E908C-6E64-4012-9AAB-74DE91CC31FF"
    },
    {
      "class": "text",
      "id": "4A2F3766-10A6-439E-97EA-51DBD25DE3A2"
    }
  ],
  "name": "出乘管理-出乘报道-已报道",
  "nameIsFixed": true,
  "presetDictionary": {
    "allowResizedMatching": 0,
    "height": 640,
    "name": "Android",
    "offersLandscapeVariant": 1,
    "width": 360
  },
  "resizesContent": false,
  "resizingConstraint": 63,
  "resizingType": 0,
  "rotation": 0,
  "shouldBreakMaskChain": true,
  "style": {
    "_class": "style",
    "endMarkerType": 0,
    "miterLimit": 10,
    "startMarkerType": 0,
    "windingRule": 1
  },
  "userInfo": {
    "io.magicsketch.mirror": {
      "highestQuality": 1,
      "included": 1,
      "linkedLayers": [
      ]
    }
  },
  "verticalRulerData": {
    "_class": "rulerData",
    "base": 0,
    "guides": [
    ]
  }
}