{
  "_class": "group",
  "do_objectID": "496477B3-2E5A-4B3B-A8BF-D20264E7A221",
  "exportOptions": {
    "_class": "exportOptions",
    "exportFormats": [
    ],
    "includedLayerIds": [
    ],
    "layerOptions": 0,
    "shouldTrim": false
  },
  "frame": {
    "_class": "rect",
    "constrainProportions": false,
    "height": 80,
    "width": 360,
    "x": 0,
    "y": 0
  },
  "hasClickThrough": false,
  "isFlippedHorizontal": false,
  "isFlippedVertical": false,
  "isLocked": false,
  "isVisible": true,
  "layerListExpandedType": 0,
  "layers": [
    {
      "class": "shapeGroup",
      "id": "54F8DDE3-BC0A-432F-816B-D10DB16A6B37"
    },
    {
      "class": "symbolInstance",
      "id": "B1F64D6C-FB85-406B-8BDF-DBF0A9ACCC6B"
    },
    {
      "class": "text",
      "id": "0CF45FC4-CBBE-427C-B0F5-B6928EF1AA52"
    }
  ],
  "name": "app bar",
  "nameIsFixed": true,
  "resizingConstraint": 63,
  "resizingType": 0,
  "rotation": 0,
  "shouldBreakMaskChain": false,
  "style": {
    "_class": "style",
    "endDecorationType": 0,
    "miterLimit": 10,
    "startDecorationType": 0
  }
}